fastq_file_utils/__init__.py
fastq_file_utils/console_helper.py
fastq_file_utils/constants.py
fastq_file_utils/file_utils.py
fastq_file_utils/system_caller.py
fastq_file_utils/validate_fastq_file.py
fastq_file_utils-0.1.0.dist-info/AUTHORS.rst
fastq_file_utils-0.1.0.dist-info/METADATA
fastq_file_utils-0.1.0.dist-info/WHEEL
fastq_file_utils-0.1.0.dist-info/entry_points.txt
fastq_file_utils-0.1.0.dist-info/top_level.txt
fastq_file_utils-0.1.0.dist-info/RECORD
