Metadata-Version: 2.2
Name: fastq_file_utils
Version: 0.1.0
Summary: A collection of Python scripts for working with FASTQ files.
Author-email: Jaideep Sundaram <jai.python3@gmail.com>
Maintainer-email: Jaideep Sundaram <jai.python3@gmail.com>
License: Not open source
Project-URL: Homepage, https://github.com/jai-python3/fastq-file-utils
Keywords: fastq_file_utils
Classifier: Development Status :: 5 - Production/Stable
Classifier: Intended Audience :: Developers
Classifier: Natural Language :: English
Classifier: Programming Language :: Python :: 3.10
Requires-Python: >=3.10
License-File: AUTHORS.rst
Requires-Dist: Click>=7.0
Requires-Dist: PyYAML
Requires-Dist: Rich
Requires-Dist: singleton-decorator
Provides-Extra: dev
Requires-Dist: coverage; extra == "dev"
Requires-Dist: mypy; extra == "dev"
Requires-Dist: pytest; extra == "dev"
Requires-Dist: ruff; extra == "dev"
